[
  { "id": 1, "question_text": "Only after the final variables had been recalibrated ____ a pattern begin to emerge.", "option_a": "did", "option_b": "had", "option_c": "was", "option_d": "would", "correct_option": "a", "level": "Advanced" },
  { "id": 2, "question_text": "Hardly ____ revising the report when the board demanded another rewrite.", "option_a": "had she finished", "option_b": "she finished", "option_c": "she had been finishing", "option_d": "she has finished", "correct_option": "a", "level": "Advanced" },
  { "id": 3, "question_text": "No sooner ____ the new policy announced than tensions rose.", "option_a": "was", "option_b": "had", "option_c": "has been", "option_d": "have", "correct_option": "b", "level": "Advanced" },
  { "id": 4, "question_text": "Under no circumstances ____ the encrypted file shared outside the department.", "option_a": "will be", "option_b": "should be", "option_c": "must be", "option_d": "should", "correct_option": "c", "level": "Advanced" },
  { "id": 5, "question_text": "Were he to have acknowledged the discrepancy earlier, the fallout ____ less damaging.", "option_a": "would be", "option_b": "would have been", "option_c": "is", "option_d": "was", "correct_option": "b", "level": "Advanced" },
  { "id": 6, "question_text": "Scarcely ____ to question the premise when counterarguments appeared.", "option_a": "had they begun", "option_b": "they began", "option_c": "were they beginning", "option_d": "they had begun", "correct_option": "a", "level": "Advanced" },
  { "id": 7, "question_text": "Only by cross-verifying external datasets ____ the anomaly explained.", "option_a": "was", "option_b": "could", "option_c": "has", "option_d": "had been", "correct_option": "b", "level": "Advanced" },
  { "id": 8, "question_text": "Should the negotiations ____ unexpectedly, alternative strategies must be deployed.", "option_a": "collapse", "option_b": "collapsed", "option_c": "be collapsing", "option_d": "have collapsed", "correct_option": "a", "level": "Advanced" },
  { "id": 9, "question_text": "Had the committee acted sooner, the crisis ____ entirely.", "option_a": "would avoid", "option_b": "would have been avoided", "option_c": "was avoided", "option_d": "would be avoided", "correct_option": "b", "level": "Advanced" },
  { "id": 10, "question_text": "Not until the results were reanalyzed ____ how flawed the assumptions were.", "option_a": "the team realized", "option_b": "did the team realize", "option_c": "had the team realized", "option_d": "was the team realizing", "correct_option": "b", "level": "Advanced" },
  { "id": 11, "question_text": "Rarely ____ a correlation as complex as the one identified.", "option_a": "has there appeared", "option_b": "does appear", "option_c": "is appearing", "option_d": "appeared", "correct_option": "a", "level": "Advanced" },
  { "id": 12, "question_text": "Only when combined with qualitative evidence ____ the findings gain significance.", "option_a": "the findings gain", "option_b": "do the findings gain", "option_c": "the findings gained", "option_d": "gained the findings", "correct_option": "b", "level": "Advanced" },
  { "id": 13, "question_text": "Had it not been for her intervention, the project ____ indefinitely.", "option_a": "might stall", "option_b": "might have stalled", "option_c": "might be stalled", "option_d": "should have stalled", "correct_option": "b", "level": "Advanced" },
  { "id": 14, "question_text": "Little ____ that his statement would be cited for years.", "option_a": "he expected", "option_b": "did he expect", "option_c": "he had expected", "option_d": "was he expecting", "correct_option": "b", "level": "Advanced" },
  { "id": 15, "question_text": "At no point ____ the research team aware of the hidden variables.", "option_a": "was", "option_b": "were", "option_c": "had been", "option_d": "are", "correct_option": "a", "level": "Advanced" },
  { "id": 16, "question_text": "Hardly ____ the conference ended when participants began debating online.", "option_a": "had", "option_b": "has", "option_c": "was", "option_d": "have", "correct_option": "a", "level": "Advanced" },
  { "id": 17, "question_text": "Were the experiment to have been replicated, the results ____ more credible.", "option_a": "would become", "option_b": "would have become", "option_c": "will become", "option_d": "become", "correct_option": "b", "level": "Advanced" },
  { "id": 18, "question_text": "Not only ____ the hypothesis flawed, but it also contradicted earlier data.", "option_a": "was", "option_b": "were", "option_c": "has been", "option_d": "had been", "correct_option": "a", "level": "Advanced" },
  { "id": 19, "question_text": "Only with a more rigorous sampling method ____ statistically valid conclusions.", "option_a": "can we draw", "option_b": "we can draw", "option_c": "we draw", "option_d": "we can have drawn", "correct_option": "a", "level": "Advanced" },
  { "id": 20, "question_text": "Were she not so meticulous, the inconsistencies ____ unnoticed.", "option_a": "might go", "option_b": "might have gone", "option_c": "would go", "option_d": "will go", "correct_option": "b", "level": "Advanced" },
  { "id": 21, "question_text": "No sooner ____ the findings published than peers demanded replication.", "option_a": "were", "option_b": "had", "option_c": "have", "option_d": "was", "correct_option": "b", "level": "Advanced" },
  { "id": 22, "question_text": "Should the assumptions ____ incorrect, the entire model collapses.", "option_a": "prove", "option_b": "proved", "option_c": "are proving", "option_d": "have proved", "correct_option": "a", "level": "Advanced" },
  { "id": 23, "question_text": "Only after examining the logs ____ the breach originated earlier.", "option_a": "they realized", "option_b": "did they realize", "option_c": "they had realized", "option_d": "was realized", "correct_option": "b", "level": "Advanced" },
  { "id": 24, "question_text": "Had the auditors looked more carefully, the discrepancies ____ detected sooner.", "option_a": "were", "option_b": "would be", "option_c": "would have been", "option_d": "may be", "correct_option": "c", "level": "Advanced" },
  { "id": 25, "question_text": "Seldom ____ a theory revised so drastically after peer review.", "option_a": "does", "option_b": "has", "option_c": "is", "option_d": "was", "correct_option": "a", "level": "Advanced" },
  { "id": 26, "question_text": "Under no condition ____ external consultants allowed access to raw datasets.", "option_a": "are", "option_b": "should be", "option_c": "must", "option_d": "should", "correct_option": "b", "level": "Advanced" },
  { "id": 27, "question_text": "Little ____ how significantly the policy would reshape the sector.", "option_a": "was anticipated", "option_b": "did they anticipate", "option_c": "they anticipated", "option_d": "they have anticipated", "correct_option": "b", "level": "Advanced" },
  { "id": 28, "question_text": "Only when recontextualized ____ the data reveal underlying biases.", "option_a": "do", "option_b": "did", "option_c": "has", "option_d": "had", "correct_option": "a", "level": "Advanced" },
  { "id": 29, "question_text": "Had the variables been isolated, the causal link ____ confirmed.", "option_a": "would be", "option_b": "would have been", "option_c": "could be", "option_d": "should have been", "correct_option": "b", "level": "Advanced" },
  { "id": 30, "question_text": "Hardly ____ the simulations completed when hardware failures occurred.", "option_a": "were", "option_b": "had", "option_c": "have been", "option_d": "was", "correct_option": "b", "level": "Advanced" },
  { "id": 31, "question_text": "Were he to reassess his stance, the negotiations ____ new momentum.", "option_a": "gain", "option_b": "gained", "option_c": "would gain", "option_d": "would have gained", "correct_option": "c", "level": "Advanced" },
  { "id": 32, "question_text": "No sooner ____ the networks synchronized than latency issues reappeared.", "option_a": "had", "option_b": "was", "option_c": "were", "option_d": "has", "correct_option": "a", "level": "Advanced" },
  { "id": 33, "question_text": "Only by interpreting the data longitudinally ____ meaningful conclusions.", "option_a": "are we deriving", "option_b": "can we derive", "option_c": "we derive", "option_d": "we had derived", "correct_option": "b", "level": "Advanced" },
  { "id": 34, "question_text": "Rarely ____ evidence this compelling in behavioral research.", "option_a": "has there been", "option_b": "there has been", "option_c": "is there", "option_d": "was there", "correct_option": "a", "level": "Advanced" },
  { "id": 35, "question_text": "Had she been fully briefed, she ____ a different recommendation.", "option_a": "would make", "option_b": "would have made", "option_c": "made", "option_d": "would be making", "correct_option": "b", "level": "Advanced" },
  { "id": 36, "question_text": "Not until the metrics were normalized ____ accurate comparisons possible.", "option_a": "were", "option_b": "was", "option_c": "are", "option_d": "have been", "correct_option": "a", "level": "Advanced" },
  { "id": 37, "question_text": "Scarcely ____ the algorithm deployed when anomalies appeared.", "option_a": "was", "option_b": "had", "option_c": "has been", "option_d": "have been", "correct_option": "b", "level": "Advanced" },
  { "id": 38, "question_text": "Only when the context was broadened ____ the trend become visible.", "option_a": "does", "option_b": "did", "option_c": "had", "option_d": "was", "correct_option": "b", "level": "Advanced" },
  { "id": 39, "question_text": "Were the findings to contradict expectations, the model ____ reassessed.", "option_a": "is", "option_b": "will be", "option_c": "would be", "option_d": "would have been", "correct_option": "c", "level": "Advanced" },
  { "id": 40, "question_text": "At no stage ____ the correlation statistically significant.", "option_a": "was", "option_b": "has been", "option_c": "is", "option_d": "had been", "correct_option": "a", "level": "Advanced" },
  { "id": 41, "question_text": "Had conditions been optimal, the results ____ even more robust.", "option_a": "will become", "option_b": "would become", "option_c": "would have become", "option_d": "became", "correct_option": "c", "level": "Advanced" },
  { "id": 42, "question_text": "Hardly ____ verifying the data when contradictory values surfaced.", "option_a": "did they finish", "option_b": "had they finished", "option_c": "they finished", "option_d": "they had been finishing", "correct_option": "b", "level": "Advanced" },
  { "id": 43, "question_text": "Only by triangulating independent sources ____ objectivity established.", "option_a": "can be", "option_b": "was", "option_c": "is", "option_d": "could be", "correct_option": "b", "level": "Advanced" },
  { "id": 44, "question_text": "No sooner ____ the new protocol implemented than compatibility issues emerged.", "option_a": "was", "option_b": "had", "option_c": "has been", "option_d": "were", "correct_option": "b", "level": "Advanced" },
  { "id": 45, "question_text": "Were he not constrained by deadlines, he ____ further refinements.", "option_a": "will attempt", "option_b": "would attempt", "option_c": "would have attempted", "option_d": "is attempting", "correct_option": "b", "level": "Advanced" },
  { "id": 46, "question_text": "Under no circumstances ____ analysts modify the raw figures.", "option_a": "are", "option_b": "should", "option_c": "must be", "option_d": "were", "correct_option": "b", "level": "Advanced" },
  { "id": 47, "question_text": "Scarcely ____ the error corrected when another occurred.", "option_a": "had", "option_b": "was", "option_c": "has", "option_d": "have", "correct_option": "a", "level": "Advanced" },
  { "id": 48, "question_text": "Only after several iterations ____ the output stabilize.", "option_a": "does", "option_b": "did", "option_c": "had", "option_d": "would", "correct_option": "b", "level": "Advanced" },
  { "id": 49, "question_text": "Rarely ____ peer reviewers agree so unanimously.", "option_a": "do", "option_b": "have", "option_c": "are", "option_d": "had", "correct_option": "a", "level": "Advanced" },
  { "id": 50, "question_text": "Had the sample size been larger, the confidence interval ____ narrower.", "option_a": "will be", "option_b": "would be", "option_c": "would have been", "option_d": "was", "correct_option": "c", "level": "Advanced" },
  { "id": 51, "question_text": "Only after revisiting historical datasets ____ the predictive model show improvement.", "option_a": "did", "option_b": "had", "option_c": "was", "option_d": "would", "correct_option": "a", "level": "Advanced" },
  { "id": 52, "question_text": "Had the committee not intervened, the proposal ____ prematurely.", "option_a": "might be withdrawn", "option_b": "might have been withdrawn", "option_c": "was withdrawn", "option_d": "is withdrawn", "correct_option": "b", "level": "Advanced" },
  { "id": 53, "question_text": "Under no circumstances ____ unauthorized personnel be granted temporary access.", "option_a": "shall", "option_b": "should", "option_c": "must", "option_d": "ought", "correct_option": "b", "level": "Advanced" },
  { "id": 54, "question_text": "Hardly ____ the hypothesis formed when contradictory evidence surfaced.", "option_a": "was", "option_b": "had", "option_c": "has been", "option_d": "have been", "correct_option": "b", "level": "Advanced" },
  { "id": 55, "question_text": "No sooner ____ initial success reported than doubts were raised about methodology.", "option_a": "was", "option_b": "had", "option_c": "has been", "option_d": "have", "correct_option": "b", "level": "Advanced" },
  { "id": 56, "question_text": "Were the assumptions to prove accurate, the implications ____ far-reaching.", "option_a": "will be", "option_b": "would be", "option_c": "would have been", "option_d": "are", "correct_option": "b", "level": "Advanced" },
  { "id": 57, "question_text": "Only by assessing longitudinal data ____ subtle patterns emerge.", "option_a": "did", "option_b": "do", "option_c": "can", "option_d": "have", "correct_option": "c", "level": "Advanced" },
  { "id": 58, "question_text": "Seldom ____ researchers encounter variables so resistant to isolation.", "option_a": "are", "option_b": "have", "option_c": "do", "option_d": "did", "correct_option": "c", "level": "Advanced" },
  { "id": 59, "question_text": "Had the early warnings been acknowledged, resources ____ allocated more effectively.", "option_a": "would be", "option_b": "would have been", "option_c": "could be", "option_d": "was", "correct_option": "b", "level": "Advanced" },
  { "id": 60, "question_text": "Not until additional trials were conducted ____ the phenomenon replicable.", "option_a": "was", "option_b": "were", "option_c": "did they deem", "option_d": "had they deemed", "correct_option": "c", "level": "Advanced" },
  { "id": 61, "question_text": "Rarely ____ a peer review process proceed without significant revisions.", "option_a": "does", "option_b": "has", "option_c": "is", "option_d": "did", "correct_option": "a", "level": "Advanced" },
  { "id": 62, "question_text": "Scarcely ____ the algorithm calibrated when new inconsistencies emerged.", "option_a": "was", "option_b": "has", "option_c": "had", "option_d": "have", "correct_option": "c", "level": "Advanced" },
  { "id": 63, "question_text": "Were it not for the unforeseen variables, the outcome ____ predictable.", "option_a": "would be", "option_b": "would have been", "option_c": "was", "option_d": "is", "correct_option": "a", "level": "Advanced" },
  { "id": 64, "question_text": "Only by employing stricter controls ____ margin of error reduced.", "option_a": "was the", "option_b": "could the", "option_c": "had the", "option_d": "has the", "correct_option": "b", "level": "Advanced" },
  { "id": 65, "question_text": "No sooner ____ the abstract published than critiques appeared online.", "option_a": "was", "option_b": "had", "option_c": "is", "option_d": "has been", "correct_option": "b", "level": "Advanced" },
  { "id": 66, "question_text": "Had the correlation been linear, the projection ____ more reliable.", "option_a": "will be", "option_b": "would be", "option_c": "would have been", "option_d": "was", "correct_option": "c", "level": "Advanced" },
  { "id": 67, "question_text": "At no point ____ the analysts deviate from standardized protocols.", "option_a": "do", "option_b": "did", "option_c": "have", "option_d": "had", "correct_option": "b", "level": "Advanced" },
  { "id": 68, "question_text": "Hardly ____ the keynote address concluded when questions poured in.", "option_a": "had", "option_b": "was", "option_c": "has", "option_d": "have", "correct_option": "a", "level": "Advanced" },
  { "id": 69, "question_text": "Only when contextual factors were considered ____ the anomaly explained.", "option_a": "could be", "option_b": "was", "option_c": "could", "option_d": "was being", "correct_option": "c", "level": "Advanced" },
  { "id": 70, "question_text": "Were the department to implement the new framework, efficiency ____ immediately.", "option_a": "would improve", "option_b": "will improve", "option_c": "would have improved", "option_d": "has improved", "correct_option": "a", "level": "Advanced" },
  { "id": 71, "question_text": "Scarcely ____ to evaluate the impact when new variables were introduced.", "option_a": "had we begun", "option_b": "we began", "option_c": "were we beginning", "option_d": "we have begun", "correct_option": "a", "level": "Advanced" },
  { "id": 72, "question_text": "Not until more rigorous criteria were applied ____ the findings validated.", "option_a": "were", "option_b": "did they get", "option_c": "did they become", "option_d": "had been", "correct_option": "c", "level": "Advanced" },
  { "id": 73, "question_text": "Rarely ____ an entire dataset reclassified after publication.", "option_a": "is", "option_b": "has", "option_c": "does", "option_d": "was", "correct_option": "a", "level": "Advanced" },
  { "id": 74, "question_text": "Only by reconstructing the dataset manually ____ the missing entries identified.", "option_a": "they could", "option_b": "could they", "option_c": "can they", "option_d": "they can", "correct_option": "b", "level": "Advanced" },
  { "id": 75, "question_text": "Had he not misinterpreted the trend, he ____ a vastly different conclusion.", "option_a": "would draw", "option_b": "would have drawn", "option_c": "drew", "option_d": "will draw", "correct_option": "b", "level": "Advanced" },
  { "id": 76, "question_text": "No sooner ____ the meeting adjourned than stakeholders demanded clarifications.", "option_a": "had", "option_b": "was", "option_c": "were", "option_d": "has", "correct_option": "a", "level": "Advanced" },
  { "id": 77, "question_text": "Were she to challenge the prevailing theory, her work ____ substantial attention.", "option_a": "will gain", "option_b": "would gain", "option_c": "would have gained", "option_d": "gained", "correct_option": "b", "level": "Advanced" },
  { "id": 78, "question_text": "Hardly ____ the final parameters adjusted when the system crashed.", "option_a": "were", "option_b": "had", "option_c": "have been", "option_d": "has been", "correct_option": "b", "level": "Advanced" },
  { "id": 79, "question_text": "Only after aggregating multiple surveys ____ a consistent pattern visible.", "option_a": "is", "option_b": "was", "option_c": "did they find", "option_d": "had they found", "correct_option": "c", "level": "Advanced" },
  { "id": 80, "question_text": "At no stage ____ the trial considered ethically questionable.", "option_a": "was", "option_b": "is", "option_c": "has been", "option_d": "had", "correct_option": "a", "level": "Advanced" },
  { "id": 81, "question_text": "Had the forecast been accurate, the team ____ alternative actions.", "option_a": "would take", "option_b": "would have taken", "option_c": "might take", "option_d": "was taking", "correct_option": "b", "level": "Advanced" },
  { "id": 82, "question_text": "Rarely ____ interdisciplinary cooperation proceed this smoothly.", "option_a": "has", "option_b": "does", "option_c": "did", "option_d": "is", "correct_option": "b", "level": "Advanced" },
  { "id": 83, "question_text": "Under no circumstances ____ the data interpreted without proper citations.", "option_a": "should", "option_b": "are", "option_c": "must", "option_d": "shall", "correct_option": "a", "level": "Advanced" },
  { "id": 84, "question_text": "Scarcely ____ she present her findings when counterclaims surfaced.", "option_a": "did", "option_b": "had", "option_c": "was", "option_d": "has", "correct_option": "b", "level": "Advanced" },
  { "id": 85, "question_text": "Only by refining the predictive algorithm ____ major inaccuracies avoided.", "option_a": "were", "option_b": "can be", "option_c": "could be", "option_d": "had been", "correct_option": "c", "level": "Advanced" },
  { "id": 86, "question_text": "No sooner ____ the funding approved than the project was expanded.", "option_a": "was", "option_b": "had been", "option_c": "has been", "option_d": "is", "correct_option": "b", "level": "Advanced" },
  { "id": 87, "question_text": "Had the sampling error been detected earlier, the dataset ____ recalibrated.", "option_a": "would be", "option_b": "would have been", "option_c": "was", "option_d": "could be", "correct_option": "b", "level": "Advanced" },
  { "id": 88, "question_text": "Not until the secondary analysis was complete ____ the model stable.", "option_a": "was", "option_b": "did they find", "option_c": "had they found", "option_d": "is", "correct_option": "b", "level": "Advanced" },
  { "id": 89, "question_text": "Seldom ____ researchers confront such contradictory evidence.", "option_a": "have", "option_b": "do", "option_c": "are", "option_d": "did", "correct_option": "b", "level": "Advanced" },
  { "id": 90, "question_text": "Only when contextualized properly ____ meaningful insight.", "option_a": "does the data yield", "option_b": "the data yields", "option_c": "has the data yielded", "option_d": "did yield", "correct_option": "a", "level": "Advanced" },
  { "id": 91, "question_text": "Were it not for his skepticism, critical flaws ____ overlooked.", "option_a": "might be", "option_b": "might have been", "option_c": "would be", "option_d": "are", "correct_option": "b", "level": "Advanced" },
  { "id": 92, "question_text": "Hardly ____ the new framework implemented when unforeseen issues arose.", "option_a": "was", "option_b": "has been", "option_c": "had been", "option_d": "is", "correct_option": "c", "level": "Advanced" },
  { "id": 93, "question_text": "No sooner ____ the simulation restarted than error logs populated.", "option_a": "had", "option_b": "was", "option_c": "has", "option_d": "have", "correct_option": "a", "level": "Advanced" },
  { "id": 94, "question_text": "Only after a revised methodology was proposed ____ renewed interest.", "option_a": "was there", "option_b": "there was", "option_c": "were there", "option_d": "there were", "correct_option": "a", "level": "Advanced" },
  { "id": 95, "question_text": "Were the criteria to shift again, the predictive model ____ significant adaptation.", "option_a": "will require", "option_b": "would require", "option_c": "would have required", "option_d": "requires", "correct_option": "b", "level": "Advanced" },
  { "id": 96, "question_text": "Scarcely ____ the researchers prepare for publication when new data arrived.", "option_a": "did", "option_b": "had", "option_c": "were", "option_d": "have", "correct_option": "b", "level": "Advanced" },
  { "id": 97, "question_text": "Not until independent replication occurred ____ the theory widely accepted.", "option_a": "was", "option_b": "did", "option_c": "had", "option_d": "has been", "correct_option": "b", "level": "Advanced" },
  { "id": 98, "question_text": "Had the preliminary signals been stronger, investors ____ more swiftly.", "option_a": "would act", "option_b": "would have acted", "option_c": "acted", "option_d": "will act", "correct_option": "b", "level": "Advanced" },
  { "id": 99, "question_text": "Under no condition ____ analysts disclose draft reports to the press.", "option_a": "must", "option_b": "are", "option_c": "should", "option_d": "may", "correct_option": "c", "level": "Advanced" },
  { "id": 100, "question_text": "Only by creating a broader comparative framework ____ subtle distinctions detected.", "option_a": "could be", "option_b": "could", "option_c": "were", "option_d": "are", "correct_option": "b", "level": "Advanced" },
  { "id": 101, "question_text": "Never before ____ I encountered such a complex problem.", "option_a": "did", "option_b": "have", "option_c": "had", "option_d": "was", "correct_option": "b", "level": "Advanced" },
  { "id": 102, "question_text": "Were it not for the heavy rain, we ____ the summit by now.", "option_a": "would reach", "option_b": "would have reached", "option_c": "reached", "option_d": "will reach", "correct_option": "b", "level": "Advanced" },
  { "id": 103, "question_text": "Little ____ she know about the surprise waiting for her.", "option_a": "does", "option_b": "did", "option_c": "has", "option_d": "was", "correct_option": "b", "level": "Advanced" },
  { "id": 104, "question_text": "Should you ____ any difficulties, please contact support immediately.", "option_a": "experience", "option_b": "experienced", "option_c": "have experienced", "option_d": "experiencing", "correct_option": "a", "level": "Advanced" },
  { "id": 105, "question_text": "Had I known about the delay, I ____ a different flight.", "option_a": "booked", "option_b": "would book", "option_c": "would have booked", "option_d": "will book", "correct_option": "c", "level": "Advanced" },
  { "id": 106, "question_text": "Scarcely ____ the game started when the power went out.", "option_a": "was", "option_b": "has", "option_c": "had", "option_d": "did", "correct_option": "c", "level": "Advanced" },
  { "id": 107, "question_text": "Only by working together ____ we achieve our goals.", "option_a": "can", "option_b": "do", "option_c": "will", "option_d": "must", "correct_option": "a", "level": "Advanced" },
  { "id": 108, "question_text": "Not only ____ late, but he also forgot his presentation.", "option_a": "was he", "option_b": "he was", "option_c": "is he", "option_d": "he is", "correct_option": "a", "level": "Advanced" },
  { "id": 109, "question_text": "On no account ____ the employees be disturbed during the drill.", "option_a": "should", "option_b": "must", "option_c": "can", "option_d": "may", "correct_option": "a", "level": "Advanced" },
  { "id": 110, "question_text": "Seldom ____ one see such a magnificent display of talent.", "option_a": "does", "option_b": "is", "option_c": "has", "option_d": "will", "correct_option": "a", "level": "Advanced" },
  { "id": 111, "question_text": "Barely ____ he entered the room when the phone rang.", "option_a": "did", "option_b": "had", "option_c": "was", "option_d": "has", "correct_option": "b", "level": "Advanced" },
  { "id": 112, "question_text": "In no way ____ responsible for the damage caused.", "option_a": "am I", "option_b": "I am", "option_c": "was I", "option_d": "I was", "correct_option": "a", "level": "Advanced" },
  { "id": 113, "question_text": "Hardly ever ____ such a rude customer in this store.", "option_a": "do we get", "option_b": "we get", "option_c": "have we got", "option_d": "we have got", "correct_option": "a", "level": "Advanced" },
  { "id": 114, "question_text": "Only when the contract is signed ____ work begin.", "option_a": "does", "option_b": "can", "option_c": "will", "option_d": "shall", "correct_option": "c", "level": "Advanced" },
  { "id": 115, "question_text": "So quickly ____ the thief run that no one could catch him.", "option_a": "did", "option_b": "does", "option_c": "has", "option_d": "was", "correct_option": "a", "level": "Advanced" },
  { "id": 116, "question_text": "Such ____ the force of the storm that trees were uprooted.", "option_a": "was", "option_b": "is", "option_c": "has been", "option_d": "were", "correct_option": "a", "level": "Advanced" },
  { "id": 117, "question_text": "Not until next week ____ the results be announced.", "option_a": "will", "option_b": "do", "option_c": "are", "option_d": "have", "correct_option": "a", "level": "Advanced" },
  { "id": 118, "question_text": "Only recently ____ I realize the importance of saving money.", "option_a": "did", "option_b": "do", "option_c": "have", "option_d": "was", "correct_option": "a", "level": "Advanced" },
  { "id": 119, "question_text": "Nowhere ____ you find a better offer than this one.", "option_a": "can", "option_b": "will", "option_c": "do", "option_d": "should", "correct_option": "b", "level": "Advanced" },
  { "id": 120, "question_text": "Little ____ we know that the solution was right in front of us.", "option_a": "did", "option_b": "do", "option_c": "have", "option_d": "were", "correct_option": "a", "level": "Advanced" },
  { "id": 121, "question_text": "Were I in your shoes, I ____ the offer immediately.", "option_a": "accepted", "option_b": "would accept", "option_c": "will accept", "option_d": "would have accepted", "correct_option": "b", "level": "Advanced" },
  { "id": 122, "question_text": "Had we arrived earlier, we ____ better seats.", "option_a": "would get", "option_b": "got", "option_c": "would have got", "option_d": "had got", "correct_option": "c", "level": "Advanced" },
  { "id": 123, "question_text": "Should the weather improve, we ____ go for a picnic.", "option_a": "might", "option_b": "would", "option_c": "will", "option_d": "can", "correct_option": "c", "level": "Advanced" },
  { "id": 124, "question_text": "But for his advice, I ____ failed the exam.", "option_a": "would", "option_b": "might", "option_c": "would have", "option_d": "could", "correct_option": "c", "level": "Advanced" },
  { "id": 125, "question_text": "If it hadn't been for the traffic, we ____ on time.", "option_a": "would be", "option_b": "would have been", "option_c": "were", "option_d": "had been", "correct_option": "b", "level": "Advanced" },
  { "id": 126, "question_text": "Suppose you ____ the lottery, what would you do?", "option_a": "win", "option_b": "won", "option_c": "had won", "option_d": "winning", "correct_option": "b", "level": "Advanced" },
  { "id": 127, "question_text": "Provided that you ____ the instructions, everything will be fine.", "option_a": "follow", "option_b": "followed", "option_c": "following", "option_d": "will follow", "correct_option": "a", "level": "Advanced" },
  { "id": 128, "question_text": "Unless he ____ soon, we will leave without him.", "option_a": "arrives", "option_b": "arrived", "option_c": "arrive", "option_d": "will arrive", "correct_option": "a", "level": "Advanced" },
  { "id": 129, "question_text": "Imagine we ____ in a world without internet.", "option_a": "live", "option_b": "lived", "option_c": "living", "option_d": "will live", "correct_option": "b", "level": "Advanced" },
  { "id": 130, "question_text": "In case of emergency, ____ the glass.", "option_a": "break", "option_b": "broke", "option_c": "broken", "option_d": "breaking", "correct_option": "a", "level": "Advanced" },
  { "id": 131, "question_text": "It is high time we ____ home.", "option_a": "go", "option_b": "went", "option_c": "gone", "option_d": "going", "correct_option": "b", "level": "Advanced" },
  { "id": 132, "question_text": "I'd rather you ____ smoke in here.", "option_a": "don't", "option_b": "didn't", "option_c": "not", "option_d": "won't", "correct_option": "b", "level": "Advanced" },
  { "id": 133, "question_text": "I wish I ____ harder for the test.", "option_a": "studied", "option_b": "had studied", "option_c": "study", "option_d": "studying", "correct_option": "b", "level": "Advanced" },
  { "id": 134, "question_text": "If only I ____ the answer to the question.", "option_a": "know", "option_b": "knew", "option_c": "known", "option_d": "knowing", "correct_option": "b", "level": "Advanced" },
  { "id": 135, "question_text": "It's about time he ____ a job.", "option_a": "finds", "option_b": "found", "option_c": "finding", "option_d": "find", "correct_option": "b", "level": "Advanced" },
  { "id": 136, "question_text": "She acts as if she ____ everything.", "option_a": "knows", "option_b": "knew", "option_c": "known", "option_d": "knowing", "correct_option": "b", "level": "Advanced" },
  { "id": 137, "question_text": "I would sooner you ____ tell anyone about this.", "option_a": "don't", "option_b": "didn't", "option_c": "not", "option_d": "wouldn't", "correct_option": "b", "level": "Advanced" },
  { "id": 138, "question_text": "Whatever happens, I ____ stand by you.", "option_a": "will", "option_b": "would", "option_c": "can", "option_d": "should", "correct_option": "a", "level": "Advanced" },
  { "id": 139, "question_text": "Whether you like it or not, we ____ to go.", "option_a": "have", "option_b": "had", "option_c": "having", "option_d": "will have", "correct_option": "a", "level": "Advanced" },
  { "id": 140, "question_text": "However hard he tried, he ____ not succeed.", "option_a": "could", "option_b": "can", "option_c": "should", "option_d": "would", "correct_option": "a", "level": "Advanced" },
  { "id": 141, "question_text": "No matter how much money he makes, he ____ never satisfied.", "option_a": "is", "option_b": "was", "option_c": "be", "option_d": "been", "correct_option": "a", "level": "Advanced" },
  { "id": 142, "question_text": "Much as I ____ him, I cannot agree with his methods.", "option_a": "respect", "option_b": "respected", "option_c": "respecting", "option_d": "respects", "correct_option": "a", "level": "Advanced" },
  { "id": 143, "question_text": "Strange as it ____ seem, I actually enjoyed the lecture.", "option_a": "may", "option_b": "might", "option_c": "can", "option_d": "could", "correct_option": "a", "level": "Advanced" },
  { "id": 144, "question_text": "Try as he ____, he couldn't lift the heavy box.", "option_a": "may", "option_b": "might", "option_c": "can", "option_d": "could", "correct_option": "b", "level": "Advanced" },
  { "id": 145, "question_text": "Difficult though it ____ be, we must finish the project.", "option_a": "may", "option_b": "might", "option_c": "can", "option_d": "could", "correct_option": "a", "level": "Advanced" },
  { "id": 146, "question_text": "For all his wealth, he ____ not happy.", "option_a": "is", "option_b": "was", "option_c": "be", "option_d": "been", "correct_option": "a", "level": "Advanced" },
  { "id": 147, "question_text": "In spite of ____ tired, he continued working.", "option_a": "being", "option_b": "be", "option_c": "been", "option_d": "was", "correct_option": "a", "level": "Advanced" },
  { "id": 148, "question_text": "Despite the fact that it was raining, we ____ out.", "option_a": "went", "option_b": "go", "option_c": "gone", "option_d": "going", "correct_option": "a", "level": "Advanced" },
  { "id": 149, "question_text": "While I admit it is difficult, I ____ think it is impossible.", "option_a": "don't", "option_b": "didn't", "option_c": "not", "option_d": "won't", "correct_option": "a", "level": "Advanced" },
  { "id": 150, "question_text": "Whereas he is good at math, she ____ better at languages.", "option_a": "is", "option_b": "was", "option_c": "be", "option_d": "been", "correct_option": "a", "level": "Advanced" },
  { "id": 151, "question_text": "On the grounds that he was ill, he ____ absent from work.", "option_a": "was", "option_b": "is", "option_c": "be", "option_d": "been", "correct_option": "a", "level": "Advanced" },
  { "id": 152, "question_text": "Seeing that you are here, we ____ as well start.", "option_a": "might", "option_b": "may", "option_c": "can", "option_d": "could", "correct_option": "a", "level": "Advanced" },
  { "id": 153, "question_text": "In view of the recent events, we have decided to ____ the meeting.", "option_a": "cancel", "option_b": "canceling", "option_c": "canceled", "option_d": "cancels", "correct_option": "a", "level": "Advanced" },
  { "id": 154, "question_text": "Given that he has no experience, he ____ remarkably well.", "option_a": "did", "option_b": "does", "option_c": "done", "option_d": "doing", "correct_option": "a", "level": "Advanced" },
  { "id": 155, "question_text": "Owing to the bad weather, the flight ____ delayed.", "option_a": "was", "option_b": "is", "option_c": "be", "option_d": "been", "correct_option": "a", "level": "Advanced" },
  { "id": 156, "question_text": "Due to the fact that he was late, he ____ the bus.", "option_a": "missed", "option_b": "misses", "option_c": "missing", "option_d": "miss", "correct_option": "a", "level": "Advanced" },
  { "id": 157, "question_text": "It was not until yesterday ____ I heard the news.", "option_a": "that", "option_b": "when", "option_c": "which", "option_d": "where", "correct_option": "a", "level": "Advanced" },
  { "id": 158, "question_text": "It is John ____ is to blame for the mistake.", "option_a": "who", "option_b": "which", "option_c": "whom", "option_d": "whose", "correct_option": "a", "level": "Advanced" },
  { "id": 159, "question_text": "What I need ____ a long holiday.", "option_a": "is", "option_b": "are", "option_c": "be", "option_d": "was", "correct_option": "a", "level": "Advanced" },
  { "id": 160, "question_text": "All he did ____ complain about the food.", "option_a": "was", "option_b": "were", "option_c": "is", "option_d": "are", "correct_option": "a", "level": "Advanced" },
  { "id": 161, "question_text": "The reason why he left ____ still a mystery.", "option_a": "is", "option_b": "are", "option_c": "was", "option_d": "were", "correct_option": "a", "level": "Advanced" },
  { "id": 162, "question_text": "The place where we met ____ Paris.", "option_a": "was", "option_b": "is", "option_c": "were", "option_d": "are", "correct_option": "a", "level": "Advanced" },
  { "id": 163, "question_text": "The day when she arrived ____ rainy.", "option_a": "was", "option_b": "is", "option_c": "were", "option_d": "are", "correct_option": "a", "level": "Advanced" },
  { "id": 164, "question_text": "Whoever says that ____ lying.", "option_a": "is", "option_b": "are", "option_c": "was", "option_d": "were", "correct_option": "a", "level": "Advanced" },
  { "id": 165, "question_text": "Whatever you do, ____ careful.", "option_a": "be", "option_b": "being", "option_c": "been", "option_d": "is", "correct_option": "a", "level": "Advanced" },
  { "id": 166, "question_text": "Wherever he goes, he ____ friends.", "option_a": "makes", "option_b": "make", "option_c": "making", "option_d": "made", "correct_option": "a", "level": "Advanced" },
  { "id": 167, "question_text": "Whenever I see him, he ____ smiling.", "option_a": "is", "option_b": "was", "option_c": "be", "option_d": "been", "correct_option": "a", "level": "Advanced" },
  { "id": 168, "question_text": "However much you try, you ____ change his mind.", "option_a": "cannot", "option_b": "could not", "option_c": "will not", "option_d": "shall not", "correct_option": "a", "level": "Advanced" },
  { "id": 169, "question_text": "Hardly had I reached the station ____ the train left.", "option_a": "when", "option_b": "than", "option_c": "before", "option_d": "after", "correct_option": "a", "level": "Advanced" },
  { "id": 170, "question_text": "No sooner had we started ____ it began to rain.", "option_a": "than", "option_b": "when", "option_c": "before", "option_d": "after", "correct_option": "a", "level": "Advanced" },
  { "id": 171, "question_text": "Scarcely had she spoken ____ she regretted her words.", "option_a": "when", "option_b": "than", "option_c": "before", "option_d": "after", "correct_option": "a", "level": "Advanced" },
  { "id": 172, "question_text": "Barely had he finished his meal ____ the waiter took his plate.", "option_a": "when", "option_b": "than", "option_c": "before", "option_d": "after", "correct_option": "a", "level": "Advanced" },
  { "id": 173, "question_text": "Not only is he intelligent, ____ also hardworking.", "option_a": "but he is", "option_b": "but is he", "option_c": "he is but", "option_d": "is he but", "correct_option": "a", "level": "Advanced" },
  { "id": 174, "question_text": "Not until later ____ I understand what he meant.", "option_a": "did", "option_b": "do", "option_c": "have", "option_d": "was", "correct_option": "a", "level": "Advanced" },
  { "id": 175, "question_text": "Only then ____ I realize my mistake.", "option_a": "did", "option_b": "do", "option_c": "have", "option_d": "was", "correct_option": "a", "level": "Advanced" },
  { "id": 176, "question_text": "So tired ____ I that I fell asleep immediately.", "option_a": "was", "option_b": "am", "option_c": "were", "option_d": "been", "correct_option": "a", "level": "Advanced" },
  { "id": 177, "question_text": "Such was his anger ____ he couldn't speak.", "option_a": "that", "option_b": "which", "option_c": "when", "option_d": "where", "correct_option": "a", "level": "Advanced" },
  { "id": 178, "question_text": "Never have I seen ____ a beautiful sunset.", "option_a": "such", "option_b": "so", "option_c": "very", "option_d": "too", "correct_option": "a", "level": "Advanced" },
  { "id": 179, "question_text": "Little did he know that he ____ being watched.", "option_a": "was", "option_b": "is", "option_c": "were", "option_d": "been", "correct_option": "a", "level": "Advanced" },
  { "id": 180, "question_text": "On no condition ____ you open this box.", "option_a": "must", "option_b": "should", "option_c": "can", "option_d": "may", "correct_option": "a", "level": "Advanced" },
  { "id": 181, "question_text": "Under no circumstances ____ be held responsible.", "option_a": "will I", "option_b": "I will", "option_c": "am I", "option_d": "I am", "correct_option": "a", "level": "Advanced" },
  { "id": 182, "question_text": "In no way ____ imply that you are wrong.", "option_a": "do I", "option_b": "I do", "option_c": "am I", "option_d": "I am", "correct_option": "a", "level": "Advanced" },
  { "id": 183, "question_text": "Only by studying hard ____ pass the exam.", "option_a": "can you", "option_b": "you can", "option_c": "will you", "option_d": "you will", "correct_option": "a", "level": "Advanced" },
  { "id": 184, "question_text": "Had I known, I ____ helped you.", "option_a": "would have", "option_b": "would", "option_c": "will have", "option_d": "can have", "correct_option": "a", "level": "Advanced" },
  { "id": 185, "question_text": "Were it to rain, the match ____ be cancelled.", "option_a": "would", "option_b": "will", "option_c": "can", "option_d": "must", "correct_option": "a", "level": "Advanced" },
  { "id": 186, "question_text": "Should you see him, ____ tell him to call me.", "option_a": "please", "option_b": "would", "option_c": "could", "option_d": "might", "correct_option": "a", "level": "Advanced" },
  { "id": 187, "question_text": "Assuming that it is true, what ____ we do?", "option_a": "should", "option_b": "would", "option_c": "could", "option_d": "might", "correct_option": "a", "level": "Advanced" },
  { "id": 188, "question_text": "Supposing he refuses, what ____ happen?", "option_a": "will", "option_b": "would", "option_c": "can", "option_d": "may", "correct_option": "a", "level": "Advanced" },
  { "id": 189, "question_text": "As long as you promise to be careful, you ____ go.", "option_a": "can", "option_b": "could", "option_c": "may", "option_d": "might", "correct_option": "a", "level": "Advanced" },
  { "id": 190, "question_text": "Unless you apologize, I ____ forgive you.", "option_a": "will not", "option_b": "would not", "option_c": "can not", "option_d": "may not", "correct_option": "a", "level": "Advanced" },
  { "id": 191, "question_text": "Even if it rains, we ____ go.", "option_a": "will", "option_b": "would", "option_c": "can", "option_d": "should", "correct_option": "a", "level": "Advanced" },
  { "id": 192, "question_text": "In case he comes, ____ him to wait.", "option_a": "ask", "option_b": "asked", "option_c": "asking", "option_d": "asks", "correct_option": "a", "level": "Advanced" },
  { "id": 193, "question_text": "It is important that he ____ the truth.", "option_a": "be told", "option_b": "is told", "option_c": "was told", "option_d": "been told", "correct_option": "a", "level": "Advanced" },
  { "id": 194, "question_text": "I suggest that she ____ a doctor.", "option_a": "see", "option_b": "sees", "option_c": "saw", "option_d": "seeing", "correct_option": "a", "level": "Advanced" },
  { "id": 195, "question_text": "It is essential that we ____ on time.", "option_a": "be", "option_b": "are", "option_c": "were", "option_d": "been", "correct_option": "a", "level": "Advanced" },
  { "id": 196, "question_text": "It is necessary that he ____ immediately.", "option_a": "leave", "option_b": "leaves", "option_c": "left", "option_d": "leaving", "correct_option": "a", "level": "Advanced" },
  { "id": 197, "question_text": "God ____ the Queen!", "option_a": "save", "option_b": "saves", "option_c": "saved", "option_d": "saving", "correct_option": "a", "level": "Advanced" },
  { "id": 198, "question_text": "Be that as it ____, I still disagree.", "option_a": "may", "option_b": "might", "option_c": "can", "option_d": "could", "correct_option": "a", "level": "Advanced" },
  { "id": 199, "question_text": "Come what ____, I will always love you.", "option_a": "may", "option_b": "might", "option_c": "can", "option_d": "could", "correct_option": "a", "level": "Advanced" },
  { "id": 200, "question_text": "Suffice it to ____ that we were not pleased.", "option_a": "say", "option_b": "said", "option_c": "saying", "option_d": "says", "correct_option": "a", "level": "Advanced" }
]